iiapds/__init__.py
iiapds/array.py
iiapds/binarytree.py
iiapds/node.py
iiapds-0.0.2.dist-info/LICENSE
iiapds-0.0.2.dist-info/METADATA
iiapds-0.0.2.dist-info/WHEEL
iiapds-0.0.2.dist-info/top_level.txt
iiapds-0.0.2.dist-info/RECORD
