Metadata-Version: 2.1
Name: iiapds
Version: 0.0.2
Summary: A small example package for data structure project
Home-page: UNKNOWN
Author: Charles Shan
Author-email: charles.shht@gmail.com
License: UNKNOWN
Platform: UNKNOWN
Classifier: Programming Language :: Python :: 3
Classifier: License :: OSI Approved :: MIT License
Classifier: Operating System :: OS Independent
